[{"ExerciseDate":"2023-12-14","ExerciseList":[{"ExerciseName":"Rudern","Repetitions":15,"Weight":105,"Sets":4,"MusclesTrained":"R\u00FCcken"},{"ExerciseName":"Latzug","Repetitions":12,"Weight":68,"Sets":4,"MusclesTrained":"R\u00FCcken"},{"ExerciseName":"Rudern Kurzhantel","Repetitions":15,"Weight":20,"Sets":4,"MusclesTrained":"R\u00FCcken"}]},{"ExerciseDate":"2023-12-12","ExerciseList":[{"ExerciseName":"Beinpresse","Repetitions":15,"Weight":200,"Sets":5,"MusclesTrained":"Beine"},{"ExerciseName":"Beinstrecker","Repetitions":15,"Weight":80,"Sets":4,"MusclesTrained":"Beine"},{"ExerciseName":"Beinbeuger","Repetitions":15,"Weight":40,"Sets":3,"MusclesTrained":"Beine"}]},{"ExerciseDate":"2023-12-11","ExerciseList":[{"ExerciseName":"Schr\u00E4gbankdr\u00FCcken Kurzhantel","Repetitions":12,"Weight":30,"Sets":4,"MusclesTrained":"Brust"},{"ExerciseName":"Bankdr\u00FCcken","Repetitions":15,"Weight":80,"Sets":4,"MusclesTrained":"Brust"},{"ExerciseName":"Butterfly Kabelzug","Repetitions":15,"Weight":32,"Sets":3,"MusclesTrained":"Brust"}]},{"ExerciseDate":"2023-12-08","ExerciseList":[{"ExerciseName":"Seitheben","Repetitions":15,"Weight":10,"Sets":4,"MusclesTrained":"Schultern"},{"ExerciseName":"Facepulls","Repetitions":15,"Weight":40,"Sets":4,"MusclesTrained":"Schultern"},{"ExerciseName":"Schulterpresse","Repetitions":12,"Weight":70,"Sets":4,"MusclesTrained":"Schultern"},{"ExerciseName":"Bauchmaschine","Repetitions":12,"Weight":71,"Sets":3,"MusclesTrained":"Bauch"}]}]